{
  "_id": {
    "$oid": "5ce82789bb42748aa72ff194"
  },
  "type": [
    "ap",
    "other"
  ],
  "name": "Voluntari.ly",
  "slug": "voluntari-ly",
  "about": "Voluntarily is an awesome open source project run by the Pam Fergusson Charitable Trust.\n\nWe are the committed people who are building the voluntarily.nz platform. \n\nYou can be part of this project too. Join us at github.com/voluntariily\n",
  "imgUrl": "http://alpha.voluntarily.nz/static/vlogo.svg",
  "dateAdded": {
    "$date": "2019-05-24T17:24:31.628Z"
  }
}